Metadata-Version: 1.2
Name: xnvme
Version: 0.7.1
Summary: xNVMe Cython and ctypes language-bindings for Python
Home-page: https://github.com/OpenMPDK/xNVMe
Author: Simon A. F. Lund
Author-email: os@safl.dk
License: Apache License, Version 2.0
Project-URL: Bug Tracker, https://github.com/OpenMPDK/xNVMe/issues
Platform: UNKNOWN
Classifier: Programming Language :: Python :: 3
Classifier: License :: OSI Approved :: Apache Software License
Classifier: Operating System :: OS Independent
Requires-Python: >=3.6
